README.md
setup.py
src/PassportMicroService.egg-info/PKG-INFO
src/PassportMicroService.egg-info/SOURCES.txt
src/PassportMicroService.egg-info/dependency_links.txt
src/PassportMicroService.egg-info/not-zip-safe
src/PassportMicroService.egg-info/requires.txt
src/PassportMicroService.egg-info/top_level.txt
src/passport/__init__.py
src/passport/app/__init__.py
src/passport/app/admin/__init__.py
src/passport/app/admin/traits/__init__.py
src/passport/app/admin/traits/admin_app_trait.py
src/passport/app/admin/traits/admin_base_trait.py
src/passport/app/admin/traits/admin_user_trait.py
src/passport/app/portal/__init__.py
src/passport/app/portal/traits/__init__.py
src/passport/app/portal/traits/portal_admin_app_trait.py
src/passport/app/portal/traits/portal_admin_base_trait.py
src/passport/app/portal/traits/portal_admin_user_trait.py
src/passport/app/portal/traits/portal_user_trait.py
src/passport/app/user/__init__.py
src/passport/app/user/traits/__init__.py
src/passport/app/user/traits/user_trait.py
src/passport/auth/__init__.py
src/passport/auth/auth_manager.py
src/passport/auth/middleware.py
src/passport/auth/traits.py
src/passport/core/__init__.py
src/passport/core/config.py
src/passport/core/messages.py
src/passport/core/middleware.py
src/passport/core/paginator_tools.py
src/passport/core/views.py
src/passport/model/__init__.py
src/passport/model/app.py
src/passport/model/app_manager.py
src/passport/model/app_token.py
src/passport/model/app_token_manager.py
src/passport/model/base.py
src/passport/model/group_manager.py
src/passport/model/permission_manager.py
src/passport/model/role_manager.py
src/passport/model/token.py
src/passport/model/token_manager.py
src/passport/model/user.py
src/passport/model/user_manager.py