Metadata-Version: 1.2
Name: PassportMicroService
Version: 0.0.3
Summary: passport-micro-service
Home-page: UNKNOWN
Author: NoahWang
Author-email: 234082230@qq.com
Maintainer: noahwang
Maintainer-email: 234082230@qq.com
License: UNKNOWN
Platform: UNKNOWN
